ita_logger/__init__.py
ita_logger/logger.py
ita_logger-0.1.2.dist-info/licenses/LICENSE
ita_logger-0.1.2.dist-info/METADATA
ita_logger-0.1.2.dist-info/WHEEL
ita_logger-0.1.2.dist-info/top_level.txt
ita_logger-0.1.2.dist-info/RECORD
