Metadata-Version: 2.4
Name: ita-logger
Version: 0.1.2
Summary: Add your description here
Requires-Python: >=3.12
License-File: LICENSE
Requires-Dist: dotenv>=0.9.9
Requires-Dist: pyyaml>=6.0.2
Dynamic: license-file
